bin
zombieadventure
