Metadata-Version: 1.0
Name: ZombieAdventure
Version: 1.0.3
Summary: Text-based survival adventure game in post-apocalyptic society.
Home-page: https://github.com/comatory/ZombieAdventure
Author: comatory
Author-email: osekdomains@gmail.com
License: LICENSE.txt
Platform: UNKNOWN
